meager/__init__.py
meager/http.py
meager/logger.py
meager/router.py
smol/__init__.py
smol/http.py
smol/logger.py
smol/router.py
meager-0.0.2.dist-info/LICENSE
meager-0.0.2.dist-info/METADATA
meager-0.0.2.dist-info/WHEEL
meager-0.0.2.dist-info/top_level.txt
meager-0.0.2.dist-info/RECORD
