Metadata-Version: 2.1
Name: meager
Version: 0.0.2
Summary: A really lightweight and simple API server, built on the socketserver module
Home-page: https://thevoxel.net/projects/meager
Author: Vorap
Author-email: vorap@thevoxel.net
License: GNU GPLv3
Platform: UNKNOWN
Classifier: Programming Language :: Python :: 3
Classifier: Operating System :: OS Independent
